MANIFEST.in
setup.cfg
setup.py
AdventureDocs.egg-info/PKG-INFO
AdventureDocs.egg-info/SOURCES.txt
AdventureDocs.egg-info/dependency_links.txt
AdventureDocs.egg-info/entry_points.txt
AdventureDocs.egg-info/requires.txt
AdventureDocs.egg-info/top_level.txt
adventuredocs/__init__.py
adventuredocs/adocs.py
adventuredocs/plugins/__init__.py
adventuredocs/plugins/jumpto.py
adventuredocs/plugins/progressnext.py