Metadata-Version: 1.0
Name: AdventureDocs
Version: 0.7.0
Summary: Choose your own adventure style documentation!
Home-page: https://github.com/lillian-gardenia-seabreeze/adventuredocs
Author: Lillian Gardenia Seabreeze
Author-email: lillian.gardenia.seabreeze@gmail.com
License: UNKNOWN
Keywords: cli
Platform: UNKNOWN
